sd_tools/__init__.py
sd_tools/auraflow.py
sd_tools/flux.py
sd_tools/misc.py
sd_tools/sd.py
sd_tools/sd3.py
sd_tools/sdxl.py
sd_tools/plugins/auraflow.py
sd_tools/plugins/base.py
sd_tools/plugins/canny.py
sd_tools/plugins/cfg.py
sd_tools/plugins/debug.py
sd_tools/plugins/depth.py
sd_tools/plugins/device.py
sd_tools/plugins/dpo.py
sd_tools/plugins/hyper.py
sd_tools/plugins/image.py
sd_tools/plugins/inpainting.py
sd_tools/plugins/instantid.py
sd_tools/plugins/ip_composition.py
sd_tools/plugins/ip_composition_xl.py
sd_tools/plugins/ipa.py
sd_tools/plugins/ipa_faceid.py
sd_tools/plugins/ipa_faceid_plus.py
sd_tools/plugins/ipa_faceid_portrait.py
sd_tools/plugins/ipa_plus.py
sd_tools/plugins/lcm.py
sd_tools/plugins/lightning.py
sd_tools/plugins/lora.py
sd_tools/plugins/model.py
sd_tools/plugins/model3.py
sd_tools/plugins/modelXL.py
sd_tools/plugins/model_flux.py
sd_tools/plugins/negative_prompt.py
sd_tools/plugins/offline.py
sd_tools/plugins/output.py
sd_tools/plugins/photo_maker.py
sd_tools/plugins/pipe.py
sd_tools/plugins/pipeline_stable_diffusion_xl_instantid.py
sd_tools/plugins/pose.py
sd_tools/plugins/prompt.py
sd_tools/plugins/res_adapter.py
sd_tools/plugins/run.py
sd_tools/plugins/safetensor.py
sd_tools/plugins/scheduler.py
sd_tools/plugins/seed.py
sd_tools/plugins/size.py
sd_tools/plugins/steps.py
sd_tools/plugins/tcd.py
sd_tools/plugins/utils.py
sd_tools/plugins/wrong.py
sd_tools/plugins/yoso.py
sd_tools/plugins/http/__init__.py
sd_tools/plugins/http/http.py
sd_tools/plugins/http/assets/dom.js
sd_tools/plugins/http/assets/index.css
sd_tools/plugins/http/assets/index.html
sd_tools/plugins/http/assets/index.js
sd_tools/plugins/ip_adapter/attention_processor.py
sd_tools/plugins/ip_adapter/attention_processor_faceid.py
sd_tools/plugins/ip_adapter/ip_adapter.py
sd_tools/plugins/ip_adapter/ip_adapter_faceid.py
sd_tools/plugins/ip_adapter/ip_adapter_faceid_separate.py
sd_tools/plugins/ip_adapter/resampler.py
sd_tools/plugins/ip_adapter/utils.py
sd_tools-1.6.0.dist-info/entry_points.txt
sd_tools-1.6.0.dist-info/LICENSE
sd_tools-1.6.0.dist-info/WHEEL
sd_tools-1.6.0.dist-info/METADATA
sd_tools-1.6.0.dist-info/RECORD
